greyhorse_process/__init__.py
greyhorse_process/abc.py
greyhorse_process/adapters.py
greyhorse_process/local.py
greyhorse_process/ssh.py
greyhorse_process-0.4.26.dist-info/METADATA
greyhorse_process-0.4.26.dist-info/WHEEL
greyhorse_process-0.4.26.dist-info/RECORD
